paddlejslite-0.0.2.data/purelib/paddlejslite/__init__.py
paddlejslite-0.0.2.data/purelib/paddlejslite/lite.so
paddlejslite-0.0.2.data/purelib/paddlejslite/libs/libiomp5.dylib
paddlejslite-0.0.2.data/purelib/paddlejslite/libs/libmklml.dylib
paddlejslite-0.0.2.data/scripts/paddle_lite_opt
paddlejslite-0.0.2.dist-info/METADATA
paddlejslite-0.0.2.dist-info/WHEEL
paddlejslite-0.0.2.dist-info/top_level.txt
paddlejslite-0.0.2.dist-info/RECORD
