Metadata-Version: 2.1
Name: paddlejslite
Version: 0.0.2
Summary: Paddle-Lite Library
Home-page: UNKNOWN
License: UNKNOWN
Platform: UNKNOWN
